python_blossom/__init__.py
python_blossom/client.py
python_blossom/errors.py
python_blossom-1.0.2.dist-info/METADATA
python_blossom-1.0.2.dist-info/WHEEL
python_blossom-1.0.2.dist-info/top_level.txt
python_blossom-1.0.2.dist-info/RECORD
