Metadata-Version: 2.4
Name: python-blossom
Version: 1.0.2
Summary: High-level Python client for the Blossom protocol (blob storage via Nostr auth)
Author: Jxck-S
License: MIT
Project-URL: Homepage, https://github.com/Jxck-S/python-blossom
Project-URL: Repository, https://github.com/Jxck-S/python-blossom.git
Project-URL: Issues, https://github.com/Jxck-S/python-blossom/issues
Classifier: Development Status :: 4 - Beta
Classifier: Intended Audience :: Developers
Classifier: License :: OSI Approved :: MIT License
Classifier: Programming Language :: Python :: 3
Classifier: Programming Language :: Python :: 3.11
Classifier: Programming Language :: Python :: 3.12
Classifier: Topic :: Software Development :: Libraries :: Python Modules
Requires-Python: >=3.11
Requires-Dist: requests<3.0.0,>=2.28.0
Requires-Dist: pynostr[websocket-client]>=0.3.0
Provides-Extra: dev
Requires-Dist: pytest>=7.0; extra == "dev"
Requires-Dist: pytest-cov>=4.0; extra == "dev"
Requires-Dist: black>=23.0; extra == "dev"
Requires-Dist: isort>=5.12; extra == "dev"
Requires-Dist: mypy>=1.0; extra == "dev"
